biointerface/__init__.py
biointerface/core.py
biointerface-0.4.0.dist-info/licenses/AUTHORS.rst
biointerface-0.4.0.dist-info/licenses/LICENSE
biointerface-0.4.0.dist-info/METADATA
biointerface-0.4.0.dist-info/WHEEL
biointerface-0.4.0.dist-info/top_level.txt
biointerface-0.4.0.dist-info/RECORD
