Metadata-Version: 2.4
Name: biointerface
Version: 0.4.0
Summary: BioInterface is a Biopython based package that extracts Protein-DNA interfaces in a PDB structures.
Author-email: Alessandro Pandolfi <alessandro.pandolfi@protonmail.com>
Maintainer-email: Alessandro Pandolfi <alessandro.pandolfi@protonmail.com>
License: MIT license
Project-URL: bugs, https://gitlab.com/MorfeoRenai/biointerface/-/issues
Project-URL: changelog, https://gitlab.com/MorfeoRenai/biointerface/-/blob/main/HISTORY.rst
Project-URL: homepage, https://gitlab.com/MorfeoRenai/biointerface
Classifier: Programming Language :: Python :: 3
License-File: LICENSE
License-File: AUTHORS.rst
Requires-Dist: pandas
Requires-Dist: biopython
Requires-Dist: pdbnucleicacids>=0.2.2
Provides-Extra: dev
Requires-Dist: spyder-kernels; extra == "dev"
Requires-Dist: flake8; extra == "dev"
Requires-Dist: ruff; extra == "dev"
Requires-Dist: mypy; extra == "dev"
Requires-Dist: pytest; extra == "dev"
Requires-Dist: tox; extra == "dev"
Requires-Dist: coverage; extra == "dev"
Requires-Dist: sphinx; extra == "dev"
Requires-Dist: watchdog; extra == "dev"
Requires-Dist: bump-my-version; extra == "dev"
Requires-Dist: wheel; extra == "dev"
Requires-Dist: build; extra == "dev"
Requires-Dist: twine; extra == "dev"
Dynamic: license-file
